dar_utilities/__init__.py
dar_utilities/__main__.py
dar_utilities/curator/__init__.py
dar_utilities/curator/upload.py
dar_utilities-0.4.0.dist-info/licenses/LICENSE
dar_utilities-0.4.0.dist-info/METADATA
dar_utilities-0.4.0.dist-info/WHEEL
dar_utilities-0.4.0.dist-info/top_level.txt
dar_utilities-0.4.0.dist-info/RECORD
