Metadata-Version: 2.4
Name: dar_utilities
Version: 0.4.0
Summary: Utilities for advanced users of eLTER Data asset registry
Author-email: Michal Klinka <klinka@ics.muni.cz>
License-Expression: MIT
Project-URL: Homepage, https://github.com/eLTER-RI/elter-dar-utilities
Project-URL: Issues, https://github.com/eLTER-RI/elter-dar-utilities/issues
Classifier: Programming Language :: Python :: 3
Classifier: Operating System :: OS Independent
Requires-Python: >=3.9
License-File: LICENSE
Requires-Dist: requests==2.32.3
Requires-Dist: requests-toolbelt==1.0.0
Dynamic: license-file
